gotify_handler/__init__.py
gotify_handler/gotify_handler.py
gotify_handler-1.0.3.dist-info/LICENSE
gotify_handler-1.0.3.dist-info/METADATA
gotify_handler-1.0.3.dist-info/WHEEL
gotify_handler-1.0.3.dist-info/top_level.txt
gotify_handler-1.0.3.dist-info/RECORD
