Metadata-Version: 2.1
Name: gotify-handler
Version: 1.0.3
Summary: An extremely simple logging handler for relaying log events to gotify
Author-email: Scott Conway <pypi@conway.scot>
License: MIT License
Project-URL: Home, https://github.com/scottmconway/gotify-handler
Classifier: License :: OSI Approved :: MIT License
Classifier: Operating System :: OS Independent
Classifier: Programming Language :: Python :: 3 :: Only
License-File: LICENSE
